google/cloud/metastore/__init__.py
google/cloud/metastore/gapic_version.py
google/cloud/metastore/py.typed
google/cloud/metastore_v1/__init__.py
google/cloud/metastore_v1/gapic_metadata.json
google/cloud/metastore_v1/gapic_version.py
google/cloud/metastore_v1/py.typed
google/cloud/metastore_v1/services/__init__.py
google/cloud/metastore_v1/services/dataproc_metastore/__init__.py
google/cloud/metastore_v1/services/dataproc_metastore/async_client.py
google/cloud/metastore_v1/services/dataproc_metastore/client.py
google/cloud/metastore_v1/services/dataproc_metastore/pagers.py
google/cloud/metastore_v1/services/dataproc_metastore/transports/__init__.py
google/cloud/metastore_v1/services/dataproc_metastore/transports/base.py
google/cloud/metastore_v1/services/dataproc_metastore/transports/grpc.py
google/cloud/metastore_v1/services/dataproc_metastore/transports/grpc_asyncio.py
google/cloud/metastore_v1/services/dataproc_metastore/transports/rest.py
google/cloud/metastore_v1/services/dataproc_metastore/transports/rest_base.py
google/cloud/metastore_v1/services/dataproc_metastore_federation/__init__.py
google/cloud/metastore_v1/services/dataproc_metastore_federation/async_client.py
google/cloud/metastore_v1/services/dataproc_metastore_federation/client.py
google/cloud/metastore_v1/services/dataproc_metastore_federation/pagers.py
google/cloud/metastore_v1/services/dataproc_metastore_federation/transports/__init__.py
google/cloud/metastore_v1/services/dataproc_metastore_federation/transports/base.py
google/cloud/metastore_v1/services/dataproc_metastore_federation/transports/grpc.py
google/cloud/metastore_v1/services/dataproc_metastore_federation/transports/grpc_asyncio.py
google/cloud/metastore_v1/services/dataproc_metastore_federation/transports/rest.py
google/cloud/metastore_v1/services/dataproc_metastore_federation/transports/rest_base.py
google/cloud/metastore_v1/types/__init__.py
google/cloud/metastore_v1/types/metastore.py
google_cloud_dataproc_metastore-1.18.2.dist-info/LICENSE
google_cloud_dataproc_metastore-1.18.2.dist-info/METADATA
google_cloud_dataproc_metastore-1.18.2.dist-info/WHEEL
google_cloud_dataproc_metastore-1.18.2.dist-info/top_level.txt
google_cloud_dataproc_metastore-1.18.2.dist-info/RECORD
